OSDOCR/OSDOcr.py
OSDOCR/__init__.py
OSDOCR/aux_utils/box.py
OSDOCR/aux_utils/consts.py
OSDOCR/aux_utils/graph.py
OSDOCR/aux_utils/misc.py
OSDOCR/aux_utils/parse_args.py
OSDOCR/commands/gui/ocr_editor/__init__.py
OSDOCR/commands/output/articles/__init__.py
OSDOCR/commands/output/simple/__init__.py
OSDOCR/commands/posprocessing/clean_ocr/__init__.py
OSDOCR/commands/validation/__init__.py
OSDOCR/consts/dimensions.json
OSDOCR/gui/aux_utils/utils.py
OSDOCR/gui/ocr_editor/assets/add.png
OSDOCR/gui/ocr_editor/assets/adjust_bb.png
OSDOCR/gui/ocr_editor/assets/calculate_reading_order.png
OSDOCR/gui/ocr_editor/assets/categorize_blocks.png
OSDOCR/gui/ocr_editor/assets/copy.png
OSDOCR/gui/ocr_editor/assets/delete_bin.png
OSDOCR/gui/ocr_editor/assets/find_articles.png
OSDOCR/gui/ocr_editor/assets/find_titles.png
OSDOCR/gui/ocr_editor/assets/fix_intersections.png
OSDOCR/gui/ocr_editor/assets/join_blocks.png
OSDOCR/gui/ocr_editor/assets/new_block.png
OSDOCR/gui/ocr_editor/assets/redo.png
OSDOCR/gui/ocr_editor/assets/refresh_block_id.png
OSDOCR/gui/ocr_editor/assets/remove_empty_blocks.png
OSDOCR/gui/ocr_editor/assets/reset.png
OSDOCR/gui/ocr_editor/assets/reset_block_height.png
OSDOCR/gui/ocr_editor/assets/save.png
OSDOCR/gui/ocr_editor/assets/send_block_back.png
OSDOCR/gui/ocr_editor/assets/send_block_front.png
OSDOCR/gui/ocr_editor/assets/settings.png
OSDOCR/gui/ocr_editor/assets/split_blocks.png
OSDOCR/gui/ocr_editor/assets/split_image.png
OSDOCR/gui/ocr_editor/assets/split_whitespaces.png
OSDOCR/gui/ocr_editor/assets/undo.png
OSDOCR/gui/ocr_editor/assets/unite_blocks.png
OSDOCR/gui/ocr_editor/assets/zoom_in.png
OSDOCR/gui/ocr_editor/assets/zoom_out.png
OSDOCR/gui/ocr_editor/configuration_gui.py
OSDOCR/gui/ocr_editor/layouts/ocr_editor_layout.py
OSDOCR/gui/ocr_editor/ocr_editor.py
OSDOCR/gui/osdocr_gui/layouts/extra_layout.py
OSDOCR/gui/osdocr_gui/layouts/main_layout.py
OSDOCR/gui/osdocr_gui/methods/methods.py
OSDOCR/gui/osdocr_gui/osdocr_gui.py
osdocr-0.3.1.6.dist-info/METADATA
osdocr-0.3.1.6.dist-info/WHEEL
osdocr-0.3.1.6.dist-info/entry_points.txt
osdocr-0.3.1.6.dist-info/RECORD
